horasCLI/__main__.py
horasCLI/utils.py
horasCLI-1.2.0.dist-info/METADATA
horasCLI-1.2.0.dist-info/RECORD
horasCLI-1.2.0.dist-info/WHEEL
horasCLI-1.2.0.dist-info/entry_points.txt
horasCLI-1.2.0.dist-info/top_level.txt
